beginnercodes/challenges/__init__.py
beginnercodes/challenges/test_runner.py
beginner_codes-0.1.3.dist-info/WHEEL
beginner_codes-0.1.3.dist-info/METADATA
beginner_codes-0.1.3.dist-info/RECORD
