Metadata-Version: 2.1
Name: beginner-codes
Version: 0.1.3
Summary: Official package for the Beginner.Codes Discord community.
License: MIT
Author: Zech Zimmerman
Author-email: hi@zech.codes
Requires-Python: >=3.7,<4.0
Classifier: License :: OSI Approved :: MIT License
Classifier: Programming Language :: Python :: 3
Classifier: Programming Language :: Python :: 3.7
Classifier: Programming Language :: Python :: 3.8
Classifier: Programming Language :: Python :: 3.9
Classifier: Programming Language :: Python :: 3.10
Classifier: Programming Language :: Python :: 3.11
Requires-Dist: requests (>=2.27.1,<3.0.0)
Requires-Dist: rich (>=13.6.0,<14.0.0)
